nats_sync/__init__.py
nats_sync/nats_ctx.py
nats_py_sync-0.1.1.dist-info/METADATA
nats_py_sync-0.1.1.dist-info/WHEEL
nats_py_sync-0.1.1.dist-info/licenses/LICENSE
nats_py_sync-0.1.1.dist-info/RECORD
