Metadata-Version: 2.4
Name: nats-py-sync
Version: 0.1.1
Summary: Synchronous wrapper around the native nats async library
Author-email: "l.weiler" <lucas.l.weiler@leidos.com>
Maintainer-email: "l.weiler" <lucas.l.weiler@leidos.com>
License: MIT License
License-File: LICENSE
Requires-Python: >=3.10
Requires-Dist: nats-py~=2.11
